helloworld_goofy/__init__.py
helloworld_goofy-0.1.dist-info/METADATA
helloworld_goofy-0.1.dist-info/WHEEL
helloworld_goofy-0.1.dist-info/top_level.txt
helloworld_goofy-0.1.dist-info/RECORD
