Metadata-Version: 2.4
Name: helloworld-goofy
Version: 0.1
Summary: A goofy hello world package
Author: Legendry Goofy
Author-email: godmoddev@gmail.com
Classifier: Programming Language :: Python :: 3
Classifier: License :: OSI Approved :: MIT License
Requires-Python: >=3.6
Dynamic: author
Dynamic: author-email
Dynamic: classifier
Dynamic: description
Dynamic: description-content-type
Dynamic: requires-python
Dynamic: summary
